{
	"configurations" : 
	[
		{
			"directories" : 
			[
				{
					"build" : ".",
					"jsonFile" : "directory-.-Debug-d0094a50bb2071803777.json",
					"minimumCMakeVersion" : 
					{
						"string" : "3.8"
					},
					"projectIndex" : 0,
					"source" : ".",
					"targetIndexes" : 
					[
						0
					]
				}
			],
			"name" : "Debug",
			"projects" : 
			[
				{
					"directoryIndexes" : 
					[
						0
					],
					"name" : "ThreadBarrier",
					"targetIndexes" : 
					[
						0
					]
				}
			],
			"targets" : 
			[
				{
					"directoryIndex" : 0,
					"id" : "ThreadBarrier::@6890427a1f51a3e7e1df",
					"jsonFile" : "target-ThreadBarrier-Debug-ce06eea787ed1866bc25.json",
					"name" : "ThreadBarrier",
					"projectIndex" : 0
				}
			]
		}
	],
	"kind" : "codemodel",
	"paths" : 
	{
		"build" : "E:/ThreadBarrier/out/build/x64-debug",
		"source" : "E:/ThreadBarrier"
	},
	"version" : 
	{
		"major" : 2,
		"minor" : 6
	}
}
